wraps_parse/__init__.py
wraps_parse/format.py
wraps_parse/normal.py
wraps_parse/py.typed
wraps_parse/simple.py
wraps_parse-0.1.0.dist-info/METADATA
wraps_parse-0.1.0.dist-info/WHEEL
wraps_parse-0.1.0.dist-info/licenses/LICENSE
wraps_parse-0.1.0.dist-info/RECORD
