Metadata-Version: 2.3
Name: wraps-parse
Version: 0.1.0
Summary: Parsing feature of wraps.
Project-URL: Homepage, https://github.com/nekitdev/wraps-parse
Project-URL: Chat, https://nekit.dev/chat
Project-URL: Documentation, https://nekitdev.github.io/wraps-parse
Project-URL: Funding, https://nekit.dev/funding
Project-URL: Issues, https://github.com/nekitdev/wraps-parse/issues
Project-URL: Repository, https://github.com/nekitdev/wraps-parse
Author-email: nekitdev <nekit@nekit.dev>
License: MIT License
License-File: LICENSE
Keywords: parse,python
Classifier: Development Status :: 4 - Beta
Classifier: Intended Audience :: Developers
Classifier: License :: OSI Approved :: MIT License
Classifier: Operating System :: OS Independent
Classifier: Programming Language :: Python
Classifier: Programming Language :: Python :: 3
Classifier: Programming Language :: Python :: 3.8
Classifier: Programming Language :: Python :: 3.9
Classifier: Programming Language :: Python :: 3.10
Classifier: Programming Language :: Python :: 3.11
Classifier: Programming Language :: Python :: 3.12
Classifier: Topic :: Utilities
Classifier: Typing :: Typed
Requires-Python: >=3.8
Requires-Dist: named>=1.4.2
Requires-Dist: typing-aliases>=1.10.1
Requires-Dist: typing-extensions>=4.12.2
Requires-Dist: wraps-core>=0.1.1
